telecms_bridge_base/__init__.py
telecms_bridge_base/configuration.py
telecms_bridge_base/db.py
telecms_bridge_base/encoders.py
telecms_bridge_base/logger.py
telecms_bridge_base/media_cache.py
telecms_bridge_base/messages.py
telecms_bridge_base/permissions.py
telecms_bridge_base/request.py
telecms_bridge_base/router.py
telecms_bridge_base/settings.py
telecms_bridge_base/status.py
telecms_bridge_base/__pycache__/__init__.cpython-38.pyc
telecms_bridge_base/__pycache__/settings.cpython-38.pyc
telecms_bridge_base/commands/__init__.py
telecms_bridge_base/commands/check_token.py
telecms_bridge_base/exceptions/__init__.py
telecms_bridge_base/exceptions/api.py
telecms_bridge_base/exceptions/missing_argument_error.py
telecms_bridge_base/exceptions/not_found.py
telecms_bridge_base/exceptions/permission_denied.py
telecms_bridge_base/exceptions/sql.py
telecms_bridge_base/exceptions/validation_error.py
telecms_bridge_base/fields/__init__.py
telecms_bridge_base/fields/any.py
telecms_bridge_base/fields/array.py
telecms_bridge_base/fields/boolean.py
telecms_bridge_base/fields/char.py
telecms_bridge_base/fields/datetime.py
telecms_bridge_base/fields/field.py
telecms_bridge_base/fields/integer.py
telecms_bridge_base/fields/json.py
telecms_bridge_base/fields/sql_params.py
telecms_bridge_base/fields/wkt.py
telecms_bridge_base/filters/__init__.py
telecms_bridge_base/filters/boolean_filter.py
telecms_bridge_base/filters/char_filter.py
telecms_bridge_base/filters/datetime_filter.py
telecms_bridge_base/filters/filter.py
telecms_bridge_base/filters/filter_class.py
telecms_bridge_base/filters/filter_for_dbfield.py
telecms_bridge_base/filters/integer_filter.py
telecms_bridge_base/filters/lookups.py
telecms_bridge_base/filters/model.py
telecms_bridge_base/filters/model_aggregate.py
telecms_bridge_base/filters/model_group.py
telecms_bridge_base/filters/model_m2m.py
telecms_bridge_base/filters/model_relation.py
telecms_bridge_base/filters/model_search.py
telecms_bridge_base-1.0.0.dist-info/LICENSE
telecms_bridge_base-1.0.0.dist-info/METADATA
telecms_bridge_base-1.0.0.dist-info/WHEEL
telecms_bridge_base-1.0.0.dist-info/top_level.txt
telecms_bridge_base-1.0.0.dist-info/RECORD
