Metadata-Version: 2.1
Name: telecms-bridge-base
Version: 1.0.0
Home-page: https://github.com/serviceexchange/telecms-bridge
Author: Billy Truong
Author-email: support@service.exchange
License: MIT
License-File: LICENSE
Requires-Dist: sqlalchemy
Requires-Dist: six
Requires-Dist: requests
Requires-Dist: Pillow
Requires-Dist: dateparser
Requires-Dist: prompt-toolkit (==2.0.9)
